btsnoop_parser/__init__.py
btsnoop_parser/__main__.py
btsnoop_parser/cli.py
btsnoop_parser/constants.py
btsnoop_parser/core.py
btsnoop_parser/hci_decoder.py
btsnoop_parser/utils.py
btsnoop_parser/tests/test_parser.py
btsnoop_parser-0.1.2.dist-info/licenses/LICENSE
btsnoop_parser-0.1.2.dist-info/METADATA
btsnoop_parser-0.1.2.dist-info/WHEEL
btsnoop_parser-0.1.2.dist-info/entry_points.txt
btsnoop_parser-0.1.2.dist-info/top_level.txt
btsnoop_parser-0.1.2.dist-info/RECORD
