Metadata-Version: 2.4
Name: btsnoop-parser
Version: 0.1.2
Summary: Bluetooth HCI btsnoop log parser for Android
Author-email: Kranthi <kdevprofile@gmail.com>
License-Expression: MIT
License-File: LICENSE
Dynamic: license-file
